monocdk_nag/__init__.py
monocdk_nag/py.typed
monocdk_nag/_jsii/__init__.py
monocdk_nag/_jsii/monocdk-nag@1.14.19.jsii.tgz
monocdk_nag-1.14.19.dist-info/LICENSE
monocdk_nag-1.14.19.dist-info/METADATA
monocdk_nag-1.14.19.dist-info/NOTICE
monocdk_nag-1.14.19.dist-info/WHEEL
monocdk_nag-1.14.19.dist-info/top_level.txt
monocdk_nag-1.14.19.dist-info/RECORD
