Metadata-Version: 2.1
Name: monocdk-nag
Version: 1.14.19
Summary: Check CDK applications for best practices using a combination on available rule packs.
Home-page: https://github.com/cdklabs/cdk-nag.git
Author: Arun Donti<donti@amazon.com>
License: Apache-2.0
Project-URL: Source, https://github.com/cdklabs/cdk-nag.git
Platform: UNKNOWN
Classifier: Intended Audience :: Developers
Classifier: Operating System :: OS Independent
Classifier: Programming Language :: JavaScript
Classifier: Programming Language :: Python :: 3 :: Only
Classifier: Programming Language :: Python :: 3.7
Classifier: Programming Language :: Python :: 3.8
Classifier: Programming Language :: Python :: 3.9
Classifier: Programming Language :: Python :: 3.10
Classifier: Typing :: Typed
Classifier: Development Status :: 5 - Production/Stable
Classifier: License :: OSI Approved
Requires-Python: ~=3.7
License-File: LICENSE
License-File: NOTICE
Requires-Dist: constructs (<4.0.0,>=3.2.27)
Requires-Dist: jsii (<2.0.0,>=1.59.0)
Requires-Dist: monocdk (<2.0.0,>=1.123.0)
Requires-Dist: publication (>=0.0.3)
